django_fine_uploader/__init__.py
django_fine_uploader/apps.py
django_fine_uploader/fineuploader.py
django_fine_uploader/forms.py
django_fine_uploader/models.py
django_fine_uploader/settings.py
django_fine_uploader/urls.py
django_fine_uploader/utils.py
django_fine_uploader/views.py
django_fine_uploader-0.2.0.dist-info/DESCRIPTION.rst
django_fine_uploader-0.2.0.dist-info/METADATA
django_fine_uploader-0.2.0.dist-info/RECORD
django_fine_uploader-0.2.0.dist-info/WHEEL
django_fine_uploader-0.2.0.dist-info/metadata.json
django_fine_uploader-0.2.0.dist-info/top_level.txt
