Metadata-Version: 1.1
Name: django-fine-uploader
Version: 0.2.0
Summary: Simple, Chunked and Concurrent uploads with Django + Fine Uploader
Home-page: https://github.com/douglasmiranda/django-fine-uploader
Author: Douglas Miranda
Author-email: douglasmirandasilva@gmail.com
License: MIT
Keywords: django-fine-uploader
Platform: UNKNOWN
Classifier: Development Status :: 3 - Alpha
Classifier: Framework :: Django
Classifier: Framework :: Django :: 1.10
Classifier: Intended Audience :: Developers
Classifier: License :: OSI Approved :: BSD License
Classifier: Natural Language :: English
Classifier: Programming Language :: Python :: 2
Classifier: Programming Language :: Python :: 2.7
Classifier: Programming Language :: Python :: 3
Classifier: Programming Language :: Python :: 3.4
Classifier: Programming Language :: Python :: 3.5
